httpsweet-0.0.1.data/scripts/httpsweet
httpsweetlib/__init__.py
httpsweetlib/constants.py
httpsweetlib/encoder.py
httpsweetlib/handler.py
httpsweetlib/parameters.py
httpsweetlib/request.py
httpsweetlib/server.py
httpsweetlib/utils.py
httpsweet-0.0.1.dist-info/LICENSE
httpsweet-0.0.1.dist-info/METADATA
httpsweet-0.0.1.dist-info/WHEEL
httpsweet-0.0.1.dist-info/top_level.txt
httpsweet-0.0.1.dist-info/RECORD
