Metadata-Version: 2.1
Name: httpsweet
Version: 0.0.1
Summary: An HTTP server for download and upload files
Home-page: https://gitlab.com/Zer1t0/httpsweet
Author: Eloy Pérez González
Author-email: zer1t0ps@protonmail.com
License: UNKNOWN
Platform: UNKNOWN
Classifier: Programming Language :: Python :: 3
Classifier: License :: OSI Approved :: GNU Affero General Public License v3 or later (AGPLv3+)
Classifier: Operating System :: OS Independent
Requires-Python: >=3.6
